{
  "DUMMY_USERS_DATA": [
    {
      "userComment": "Not Action 'Invalid.  This was probably illegal",
      "id": 1,
      "userName": "MAlisha Allen"
    },
    {
      "userComment": "Action 'Invalid.  This was probably illegal",
      "id": 2,
      "userName": "Alisha Pena"
    },
    {
      "userComment": "Not Action 'Invalid.  This was probably illegal",
      "id": 3,
      "userName": "Phil Pena"
    },
    {
      "userComment": "Action 'Invalid.  This was probably illegal",
      "id": 4,
      "userName": "Alisha Phillips"
    },
    {
      "userComment": "Not Action 'Invalid.  This was probably illegal",
      "id": 5,
      "userName": "MAlisha Ashely"
    },
    {
      "userComment": "Action 'Invalid.  This was probably illegal",
      "id": 6,
      "userName": "Pilot Pete"
    },
    {
      "userName": "Wahab",
      "userComment": "A quick brown fox jumps over the lazy dog",
      "id": 7
    },
    {
      "userName": "Test User",
      "userComment": "Lorem ipsum dolor sit amet, consectetur adipiscing elit, sed do eiusmod tempor incididunt ut labore et dolore magna aliqua. Ut enim ad minim veniam, quis nostrud exercitation ullamco laboris nisi ut aliquip ex ea commodo consequat. Duis aute irure dolor in reprehenderit in voluptate velit esse cillum dolore eu fugiat nulla pariatur. Excepteur sint occaecat cupidatat non proident, sunt in culpa qui officia deserunt mollit anim id est laborum.",
      "id": 8
    },
    {
      "userName": "Abdul Wahab",
      "userComment": "Lorem ipsum dolor sit amet, consectetur adipiscing elit, sed do eiusmod tempor incididunt ut labore et dolore magna aliqua. ",
      "id": 9
    },
    {
      "userName": "Test User",
      "userComment": "jbhasjkhahksjda",
      "id": 10
    },
    {
      "userName": "Test",
      "userComment": "jbhasjkhahksjda",
      "id": 11
    },
    {
      "userName": "dfgdfg",
      "userComment": "dfgdgdgdgdfg",
      "id": 12
    },
    {
      "userName": "sdfsdf",
      "userComment": "sdfsdfsdfsdfsdfsdf",
      "id": 13
    },
    {
      "userName": "Mustansar",
      "userComment": "Musitansar",
      "id": 14
    },
    {
      "userName": "Abbas Ali",
      "userComment": "A quick brown fox jumps over the lazy dog",
      "id": 15
    },
    {
      "userName": "Shahzaib",
      "userComment": "A quick brown fox jumps over the lazy dog",
      "id": 16
    },
    {
      "userName": "Talha",
      "userComment": "A quick brown fox jumps over the lazy dog",
      "id": 17
    },
    {
      "userName": "Sanan",
      "userComment": "A quick brown fox jumps over the lazy dog",
      "id": 18
    },
    {
      "userName": "Inzamam",
      "userComment": "A quick brown fox jumps over the lazy dog",
      "id": 19
    },
    {
      "userName": "sdfsdf",
      "userComment": "A quick brown fox jumps over the lazy dog",
      "id": 20
    },
    {
      "userName": "James",
      "userComment": "A quick brown fox jumps over the lazy dog",
      "id": 21
    },
    {
      "userName": "Ali Abbas",
      "userComment": "A quick brown fox jumps over the lazy dog",
      "id": 22
    },
    {
      "userName": "Testing",
      "userComment": "Testing",
      "id": 23
    },
    {
      "userName": "Testing 2",
      "userComment": "Test 2",
      "id": 24
    },
    {
      "userName": "Test 3",
      "userComment": "Test 3",
      "id": 25
    },
    {
      "userName": "Test 4",
      "userComment": "Test 4",
      "id": 26
    }
  ]
}